{
  "bookingReference": "CHERRY202411231299",
  "voyageDetails": {
    "vesselName": "APL CHANGI",
    "voyageNumber": "OFLQ2E1MA"
  },
  "routeDetails": {
    "placeOfReceipt": "NINGBO, CHINA",
    "portOfLoading": "NINGBO, CHINA",
    "portOfDischarge": "ROTTERDAM, NETHERLANDS",
    "placeOfDelivery": "ROTTERDAM, NETHERLANDS"
  },
  "paymentDetails": {
    "freightPaymentTerms": "PREPAID",
    "freightPayableAt": "NINGBO, CHINA"
  },
  "documentationDetails": {
    "blType": "ORIGINAL",
    "numberOfOriginalBLs": 3,
    "numberOfCopies": 5
  },
  "partyDetails": {
    "shipper": {
      "name": "OMEGA INDUSTRIES INC.",
      "address": "NO. 123, FUXING ROAD, HANGZHOU, ZHEJIAN, CHINA 310000",
      "telephone": "+86-571-87654321",
      "fax": "+86-571-87654322"
    },
    "consignee": {
      "name": "DELTA TRADING CO.",
      "address": "CALLE MAYOR, 12, 28001 MADRID, SPAIN",
      "telephone": "+34-91-555-6666",
      "fax": "+34-91-555-6667"
    },
    "notifyParty": {
      "name": "DELTA TRADING CO. LTD",
      "address": "NO. 1, FUXING ROAD, HANGZHOU, ZHEJIAN, CHINA 310000",
      "telephone": "+86-571-87654300",
      "fax": "+86-571-87654301"
    }
  },
  "shippingTerm": "CY/DOOR",
  "hsCode": "940161",
  "commodityDescription": "OFFICE CHAIRS",
  "containers": [
    {
      "containerNumber": "CONT2142670",
      "sealNumber": "SEAL446695",
      "numberOfPackages": 68,
      "packageType": "BOXES",
      "grossWeight": 17617.19,
      "measurement": 26.73
    },
    {
      "containerNumber": "CONT1875248",
      "sealNumber": "SEAL580069",
      "numberOfPackages": 25,
      "packageType": "BOXES",
      "grossWeight": 8772.87,
      "measurement": 38.18
    },
    {
      "containerNumber": "CONT3143943",
      "sealNumber": "SEAL582146",
      "numberOfPackages": 62,
      "packageType": "BOXES",
      "grossWeight": 6815.87,
      "measurement": 26.61
    },
    {
      "containerNumber": "CONT3847438",
      "sealNumber": "SEAL387785",
      "numberOfPackages": 85,
      "packageType": "BOXES",
      "grossWeight": 10926.39,
      "measurement": 30.58
    },
    {
      "containerNumber": "CONT1576821",
      "sealNumber": "SEAL941386",
      "numberOfPackages": 86,
      "packageType": "BOXES",
      "grossWeight": 13353.85,
      "measurement": 37.32
    },
    {
      "containerNumber": "CONT9031557",
      "sealNumber": "SEAL498767",
      "numberOfPackages": 14,
      "packageType": "BOXES",
      "grossWeight": 18284.17,
      "measurement": 20.26
    }
  ],
  "totalShipment": {
    "totalContainers": "6 x 45 HIGH CUBE GENERAL",
    "totalPackages": 340,
    "totalGrossWeight": 75770.34,
    "totalMeasurement": 179.68
  },
  "additionalInformation": {
    "purchaseOrderNumber": "PO123456",
    "salesOrderNumber": "SO789012",
    "lcDetails": {
      "lcNumber": "LC1234567890"
    },
    "certificateDetails": "1234567890",
    "originalBLDistribution": {
      "name": "DELTA TRADING CO. LTD",
      "address": "NO. 1, FUXING ROAD, HANGZHOU, ZHEJIAN, CHINA 310000",
      "telephone": "+86-571-87654300",
      "fax": "+86-571-87654301"
    },
    "originalInvoiceDistribution": {
      "name": "DELTA TRADING CO. LTD",
      "address": "NO. 1, FUXING ROAD, HANGZHOU, ZHEJIAN, CHINA 310000",
      "telephone": "+86-571-87654300",
      "fax": "+86-571-87654301"
    },
    "onboardDate": "2024-12-06 18:00",
    "additionalRemarks": "NO SPECIAL INSTRUCTIONS"
  }
}