{
  "bookingReference": "CHERRY202411295321",
  "customerName": "ABC GLOBAL LOGISTICS LTD",
  "shipperName": "XYZ MANUFACTURING CO. LTD",
  "invoiceReceiver": "ABC GLOBAL LOGISTICS LTD",
  "voyageDetails": {
    "vesselName": "SHIP_2409",
    "voyageNumber": "3408"
  },
  "cargoDetails": {
    "hsCode": "950300",
    "chapterDescription": "TOYS, GAMES AND SPORTING GOODS",
    "commodity": "GENERAL"
  },
  "containerDetails": {
    "size": "40 STANDARD",
    "type": "TANK",
    "quantity": 7
  },
  "routeDetails": {
    "placeOfReceipt": "SHANGHAI",
    "portOfLoading": "SHANGHAI",
    "portOfDischarge": "ROTTERDAM",
    "placeOfDelivery": "ROTTERDAM"
  },
  "scheduleDetails": {
    "estimatedArrivalAtLoadingPort": "2024-12-15 10:00",
    "estimatedDepartureFromLoadingPort": "2024-12-16 18:00",
    "estimatedArrivalAtDischargePort": "2025-01-10 08:00"
  },
  "emptyContainerPickupLocation": "SHANGHAI",
  "shippingTerm": "CY/CY",
  "remarks": "NO SPECIAL INSTRUCTIONS",
  "cargoType": "GENERAL"
}