{
  "bookingReference": "CHERRY202411192498",
  "customerName": "GLOBAL TRADING SOLUTIONS INC",
  "shipperName": "PREMIUM MACHINERY LTD",
  "invoiceReceiver": "GLOBAL TRADING SOLUTIONS INC",
  "voyageDetails": {
    "vesselName": "CMA CGM VASCO DE GAMA",
    "voyageNumber": "OFLQLW1MA"
  },
  "cargoDetails": {
    "hsCode": "843149",
    "chapterDescription": "PARTS FOR MACHINERY OF HEADING 8425, 8426, 8427, 8428, 8429, 8431 OR 8432, EXCEPT PARTS FOR MACHINES OF HEADING 8425, 8426 OR 8427",
    "commodity": "OUT-OF-GAUGE INDUSTRIAL EQUIPMENT"
  },
  "containerDetails": {
    "size": "40 HIGH CUBE",
    "type": "OPEN TOP",
    "quantity": 3
  },
  "routeDetails": {
    "placeOfReceipt": "NINGBO, CHINA",
    "portOfLoading": "NINGBO, CHINA",
    "portOfDischarge": "HAMBURG, GERMANY",
    "placeOfDelivery": "HAMBURG, GERMANY"
  },
  "scheduleDetails": {
    "estimatedArrivalAtLoadingPort": "2024-11-22 10:00",
    "estimatedDepartureFromLoadingPort": "2024-11-24 16:00",
    "estimatedArrivalAtDischargePort": "2024-12-27 09:00"
  },
  "emptyContainerPickupLocation": "NINGBO, CHINA",
  "shippingTerm": "CY/DOOR",
  "remarks": "CONTAINER TYPE: OPEN TOP, OUT OF GAUGE CARGO, LxWxH(mm): 8447x2912x2183, VALUE: USD634,233",
  "cargoType": "OUT_OF_GAUGE"
}