{
  "bookingReference": "CHERRY202411095519",
  "customerName": "OMEGA LOGISTICS LTD.",
  "shipperName": "DELTA MANUFACTURING CO. INC.",
  "invoiceReceiver": "OMEGA LOGISTICS LTD.",
  "voyageDetails": {
    "vesselName": "SHIP_1852",
    "voyageNumber": "2851"
  },
  "cargoDetails": {
    "hsCode": "871690",
    "chapterDescription": "TRAILERS AND SEMI-TRAILERS",
    "commodity": "SPECIALIZED TRAILER FOR HEAVY EQUIPMENT TRANSPORT"
  },
  "containerDetails": {
    "size": "40 OPEN TOP",
    "type": "OPEN TOP",
    "quantity": 1
  },
  "routeDetails": {
    "placeOfReceipt": "NINGBO, CHINA",
    "portOfLoading": "NINGBO, CHINA",
    "portOfDischarge": "ROTTERDAM, NETHERLANDS",
    "placeOfDelivery": "ROTTERDAM, NETHERLANDS"
  },
  "scheduleDetails": {
    "estimatedArrivalAtLoadingPort": "2024-11-15 12:00",
    "estimatedDepartureFromLoadingPort": "2024-11-16 18:00",
    "estimatedArrivalAtDischargePort": "2024-12-20 08:00"
  },
  "emptyContainerPickupLocation": "NINGBO, CHINA",
  "shippingTerm": "CFS/CY",
  "remarks": "CONTAINER TYPE: OPEN TOP, OUT OF GAUGE CARGO, LxWxH(mm): 5170x2367x2042, 21 DAYS FREE TIME AT DESTINATION",
  "cargoType": "OUT_OF_GAUGE"
}