{
  "bookingReference": "CHERRY202410228075",
  "voyageDetails": {
    "vesselName": "CMA CGM ZHENG HE",
    "voyageNumber": "2435EW"
  },
  "routeDetails": {
    "placeOfReceipt": "NINGBO, CHINA",
    "portOfLoading": "NINGBO, CHINA",
    "portOfDischarge": "ROTTERDAM, NETHERLANDS",
    "placeOfDelivery": "ROTTERDAM, NETHERLANDS"
  },
  "paymentDetails": {
    "freightPaymentTerms": "PREPAID",
    "freightPayableAt": "NINGBO, CHINA"
  },
  "documentationDetails": {
    "blType": "Sea Waybill",
    "numberOfOriginalBLs": 3,
    "numberOfCopies": 2
  },
  "partyDetails": {
    "shipper": {
      "name": "GREEN EARTH LOGISTICS",
      "address": "No. 123, Xinghai Road, Ningbo, Zhejiang Province, China",
      "telephone": "+86-574-8888-6666",
      "fax": "+86-574-8888-5555"
    },
    "consignee": {
      "name": "SUNRISE TRADING CO.",
      "address": "123 Main Street, Amsterdam, Netherlands",
      "telephone": "+31-20-1234-5678",
      "fax": "+31-20-1234-5679"
    },
    "notifyParty": {
      "name": "SUNRISE TRADING CO.",
      "address": "123 Main Street, Amsterdam, Netherlands",
      "telephone": "+31-20-1234-5678",
      "fax": "+31-20-1234-5679"
    }
  },
  "shippingTerm": "CIF",
  "hsCode": "902300",
  "commodityDescription": "MEDICAL EQUIPMENT",
  "containers": [
    {
      "containerNumber": "CMLU1234567",
      "sealNumber": "123456",
      "marksAndNumbers": "ABC123",
      "numberOfPackages": 50,
      "packageType": "CARTONS",
      "cargoDescription": "MEDICAL EQUIPMENT AS PER INVOICE",
      "grossWeight": 12000.0,
      "measurement": 30.0
    },
    {
      "containerNumber": "CMLU7654321",
      "sealNumber": "654321",
      "marksAndNumbers": "ABC789",
      "numberOfPackages": 50,
      "packageType": "CARTONS",
      "cargoDescription": "MEDICAL EQUIPMENT AS PER INVOICE",
      "grossWeight": 12000.0,
      "measurement": 30.0
    },
    {
      "containerNumber": "CMLU8765432",
      "sealNumber": "876543",
      "marksAndNumbers": "DEF123",
      "numberOfPackages": 50,
      "packageType": "CARTONS",
      "cargoDescription": "MEDICAL EQUIPMENT AS PER INVOICE",
      "grossWeight": 12000.0,
      "measurement": 30.0
    },
    {
      "containerNumber": "CMLU2345678",
      "sealNumber": "234567",
      "marksAndNumbers": "DEF789",
      "numberOfPackages": 50,
      "packageType": "CARTONS",
      "cargoDescription": "MEDICAL EQUIPMENT AS PER INVOICE",
      "grossWeight": 12000.0,
      "measurement": 30.0
    },
    {
      "containerNumber": "CMLU6543210",
      "sealNumber": "654321",
      "marksAndNumbers": "GHI123",
      "numberOfPackages": 50,
      "packageType": "CARTONS",
      "cargoDescription": "MEDICAL EQUIPMENT AS PER INVOICE",
      "grossWeight": 12000.0,
      "measurement": 30.0
    }
  ],
  "totalShipment": {
    "totalContainers": "FIVE (20' DRY) CONTAINERS",
    "totalPackages": 250,
    "packageType": "CARTONS",
    "totalGrossWeight": 60000.0,
    "totalMeasurement": 150.0
  },
  "additionalInformation": {
    "purchaseOrderNumber": "PO123456",
    "salesOrderNumber": "SO789012",
    "lcDetails": {
      "lcNumber": "LC1234567890"
    },
    "certificateDetails": "Certificate of Origin",
    "originalBLDistribution": {
      "name": "SUNRISE TRADING CO.",
      "address": "123 Main Street, Amsterdam, Netherlands",
      "telephone": "+31-20-1234-5678",
      "fax": "+31-20-1234-5679"
    },
    "originalInvoiceDistribution": {
      "name": "GREEN EARTH LOGISTICS",
      "address": "No. 123, Xinghai Road, Ningbo, Zhejiang Province, China",
      "telephone": "+86-574-8888-6666",
      "fax": "+86-574-8888-5555"
    },
    "onboardDate": "2024-10-28 10:00",
    "additionalRemarks": "Please ensure proper documentation for medical equipment import."
  },
  "outOfGaugeDimensions": {
    "length": 0,
    "width": 0,
    "height": 0,
    "overWidth": 0,
    "overHeight": 0
  }
}