{
  "bookingReference": "CHERRY202411114314",
  "voyageDetails": {
    "vesselName": "SHIP_5899",
    "voyageNumber": "6898"
  },
  "routeDetails": {
    "placeOfReceipt": "LE HAVRE",
    "portOfLoading": "LE HAVRE",
    "portOfDischarge": "ROTTERDAM",
    "placeOfDelivery": "ROTTERDAM"
  },
  "paymentDetails": {
    "freightPaymentTerms": "PREPAID",
    "freightPayableAt": "LE HAVRE"
  },
  "documentationDetails": {
    "blType": "ORIGINAL",
    "numberOfOriginalBLs": 3,
    "numberOfCopies": 7
  },
  "partyDetails": {
    "shipper": {
      "name": "SIEMENS AG",
      "address": "WITTHAUSSTRASSE 10, 80336 MUNICH, GERMANY",
      "country": "GERMANY",
      "additionalInfo": "",
      "telephone": "+49 89 636-31000",
      "fax": "+49 89 636-31001",
      "email": "INFO@SIEMENS.COM"
    },
    "consignee": {
      "name": "DHL GLOBAL FORWARDING GMBH",
      "address": "STRASSENBANK 4, 60329 FRANKFURT AM MAIN, GERMANY",
      "country": "GERMANY",
      "telephone": "+49 69 5005 0",
      "fax": "+49 69 5005 1111",
      "email": "INFO@DHL.COM",
      "personincharge": "ANNA MEIER"
    },
    "notifyParty": {
      "name": "DHL GLOBAL FORWARDING GMBH",
      "address": "STRASSENBANK 4, 60329 FRANKFURT AM MAIN, GERMANY",
      "country": "GERMANY",
      "telephone": "+49 69 5005 0",
      "fax": "+49 69 5005 1111",
      "email": "INFO@DHL.COM"
    }
  },
  "shippingTerm": "CY/CY",
  "hsCode": "854370",
  "commodityDescription": "INDUSTRIAL HEATING ELEMENTS",
  "containers": [
    {
      "containerNumber": "CONT7292454",
      "sealNumber": "SEAL882276",
      "numberOfPackages": 35,
      "packageType": "BOXES",
      "grossWeight": 10794.35,
      "measurement": 23.35
    },
    {
      "containerNumber": "CONT5423024",
      "sealNumber": "SEAL556819",
      "numberOfPackages": 20,
      "packageType": "BOXES",
      "grossWeight": 15110.46,
      "measurement": 27.91
    },
    {
      "containerNumber": "CONT1841944",
      "sealNumber": "SEAL291886",
      "numberOfPackages": 36,
      "packageType": "BOXES",
      "grossWeight": 19183.58,
      "measurement": 21.1
    },
    {
      "containerNumber": "CONT5163615",
      "sealNumber": "SEAL524148",
      "numberOfPackages": 38,
      "packageType": "BOXES",
      "grossWeight": 5693.96,
      "measurement": 29.59
    },
    {
      "containerNumber": "CONT1068470",
      "sealNumber": "SEAL684449",
      "numberOfPackages": 32,
      "packageType": "BOXES",
      "grossWeight": 7104.95,
      "measurement": 35.49
    },
    {
      "containerNumber": "CONT6180655",
      "sealNumber": "SEAL552380",
      "numberOfPackages": 36,
      "packageType": "BOXES",
      "grossWeight": 11284.17,
      "measurement": 23.04
    }
  ],
  "totalShipment": {
    "totalContainers": "6 x 20 STANDARD GENERAL",
    "totalPackages": 197,
    "totalGrossWeight": 69171.47,
    "totalMeasurement": 160.48
  },
  "additionalInformation": {
    "lcDetails": {
      "lcNumber": "LC231111001"
    },
    "certificateDetails": [
      "411252403578X",
      "411252403579Y"
    ],
    "originalBLDistribution": {
      "name": "DHL GLOBAL FORWARDING GMBH",
      "address": "STRASSENBANK 4, 60329 FRANKFURT AM MAIN, GERMANY",
      "telephone": "+49 69 5005 0",
      "fax": "+49 69 5005 1111",
      "email": "INFO@DHL.COM"
    },
    "originalInvoiceDistribution": {
      "name": "DHL GLOBAL FORWARDING GMBH",
      "address": "STRASSENBANK 4, 60329 FRANKFURT AM MAIN, GERMANY",
      "telephone": "+49 69 5005 0",
      "fax": "+49 69 5005 1111",
      "email": "INFO@DHL.COM"
    },
    "onboardDate": "2024-11-16 18:00",
    "additionalRemarks": "NO SPECIAL INSTRUCTIONS"
  }
}