{
  "bookingReference": "CHERRY202410014584",
  "voyageDetails": {
    "vesselName": "SHIP_4946",
    "voyageNumber": "5945"
  },
  "routeDetails": {
    "placeOfReceipt": "NINGBO",
    "portOfLoading": "NINGBO",
    "portOfDischarge": "ALGECIRAS",
    "placeOfDelivery": "ALGECIRAS"
  },
  "paymentDetails": {
    "freightPaymentTerms": "PREPAID",
    "freightPayableAt": "NINGBO, CHINA"
  },
  "documentationDetails": {
    "blType": "ORIGINAL",
    "numberOfOriginalBLs": 3,
    "numberOfCopies": 5
  },
  "partyDetails": {
    "shipper": {
      "name": "GLOBAL IMPORT EXPORT CO.",
      "address": "NO. 1234, HONGQI ROAD, SHANGHAI, CHINA",
      "telephone": "+86-21-5678-9012",
      "fax": "+86-21-5678-9013"
    },
    "consignee": {
      "name": "ASIA PACIFIC LOGISTICS LTD",
      "address": "CALLE REAL, 123, ALGECIRAS, SPAIN",
      "telephone": "+34-956-7890-12",
      "fax": "+34-956-7890-13",
      "email": "INFO@ASIAPACIFICLOGISTICS.ES",
      "contactPerson": "MARIA GARCIA"
    },
    "notifyParty": {
      "name": "ASIA PACIFIC LOGISTICS LTD"
    }
  },
  "shippingTerm": "CFS/CY",
  "hsCode": "950300",
  "commodityDescription": "TOY, GAMES AND SPORTS REQUISITES; PARTS AND ACCESSORIES THEREOF",
  "containers": [
    {
      "containerNumber": "CONT4889440",
      "sealNumber": "SEAL897609",
      "numberOfPackages": 68,
      "packageType": "BOXES",
      "grossWeight": 8246.05,
      "measurement": 28.79
    },
    {
      "containerNumber": "CONT6695450",
      "sealNumber": "SEAL252632",
      "numberOfPackages": 47,
      "packageType": "BOXES",
      "grossWeight": 10365.8,
      "measurement": 22.56
    },
    {
      "containerNumber": "CONT3556945",
      "sealNumber": "SEAL268465",
      "numberOfPackages": 11,
      "packageType": "BOXES",
      "grossWeight": 12740.09,
      "measurement": 20.84
    },
    {
      "containerNumber": "CONT5538254",
      "sealNumber": "SEAL204967",
      "numberOfPackages": 21,
      "packageType": "BOXES",
      "grossWeight": 8173.62,
      "measurement": 21.78
    },
    {
      "containerNumber": "CONT8959528",
      "sealNumber": "SEAL288485",
      "numberOfPackages": 73,
      "packageType": "BOXES",
      "grossWeight": 7488.82,
      "measurement": 25.05
    },
    {
      "containerNumber": "CONT3815902",
      "sealNumber": "SEAL228600",
      "numberOfPackages": 42,
      "packageType": "BOXES",
      "grossWeight": 9923.24,
      "measurement": 36.84
    }
  ],
  "totalShipment": {
    "totalContainers": "6 x 40 STANDARD TANK",
    "totalPackages": 262,
    "totalGrossWeight": 56937.62,
    "totalMeasurement": 155.86
  },
  "additionalInformation": {
    "invoiceNumber": "20241023-1001",
    "documentNumber": "20241023-1001",
    "lcDetails": {
      "lcNumber": "LC1234567890"
    },
    "certificateDetails": [],
    "originalBLDistribution": {
      "name": "ASIA PACIFIC LOGISTICS LTD",
      "address": "CALLE REAL, 123, ALGECIRAS, SPAIN",
      "telephone": "+34-956-7890-12",
      "fax": "+34-956-7890-13"
    },
    "originalInvoiceDistribution": {
      "name": "ASIA PACIFIC LOGISTICS LTD",
      "address": "CALLE REAL, 123, ALGECIRAS, SPAIN",
      "telephone": "+34-956-7890-12",
      "fax": "+34-956-7890-13"
    },
    "onboardDate": "2024-10-16 18:00",
    "additionalRemarks": "NO SPECIAL INSTRUCTIONS"
  }
}