{
  "bookingReference": "CHERRY202410294177",
  "voyageDetails": {
    "vesselName": "SHIP_4847",
    "voyageNumber": "5846"
  },
  "routeDetails": {
    "placeOfReceipt": "NINGBO",
    "portOfLoading": "NINGBO",
    "portOfDischarge": "ROTTERDAM",
    "placeOfDelivery": "ROTTERDAM"
  },
  "paymentDetails": {
    "freightPaymentTerms": "PREPAID",
    "freightPayableAt": "NINGBO, CHINA"
  },
  "documentationDetails": {
    "blType": "NEGOTIABLE",
    "numberOfOriginalBLs": 3,
    "numberOfCopies": 0
  },
  "partyDetails": {
    "shipper": {
      "name": "ASIA PACIFIC MANUFACTURING CO. LTD",
      "onBehalfOf": "",
      "address": "1234 TOY ROAD, NINGBO, ZHEJIANG, CHINA 315000",
      "telephone": "+86 574 5678 9012",
      "fax": "+86 574 5678 9013",
      "email": "LIU.MEI@ASIAMFG.CN"
    },
    "consignee": {
      "name": "WORLDWIDE SHIPPING LTD.",
      "address": "888 WORLDWIDE WAY, ROTTERDAM, NETHERLANDS 3011 DP",
      "companyNumber": "1234567890",
      "telephone": "+31 10 200 3000",
      "fax": "+31 10 200 3001",
      "email": "JANSSEN.MARK@WORLDWIDESHIPPING.NL"
    },
    "notifyParty": {
      "name": "WORLDWIDE LOGISTICS LTD.",
      "address": "999 LOGISTICS LANE, ROTTERDAM, NETHERLANDS 3015 GJ"
    }
  },
  "shippingTerm": "CFS/CY",
  "hsCode": "950300",
  "commodityDescription": "TOY CARS",
  "containers": [
    {
      "containerNumber": "CONT4594047",
      "sealNumber": "SEAL326171",
      "numberOfPackages": 73,
      "packageType": "BOXES",
      "grossWeight": 14413.79,
      "measurement": 31.01
    },
    {
      "containerNumber": "CONT9003546",
      "sealNumber": "SEAL710303",
      "numberOfPackages": 86,
      "packageType": "BOXES",
      "grossWeight": 12127.53,
      "measurement": 36.68
    },
    {
      "containerNumber": "CONT9532673",
      "sealNumber": "SEAL955101",
      "numberOfPackages": 48,
      "packageType": "BOXES",
      "grossWeight": 15453.52,
      "measurement": 32.41
    },
    {
      "containerNumber": "CONT7273996",
      "sealNumber": "SEAL256566",
      "numberOfPackages": 62,
      "packageType": "BOXES",
      "grossWeight": 11116.72,
      "measurement": 29.0
    },
    {
      "containerNumber": "CONT9041598",
      "sealNumber": "SEAL423985",
      "numberOfPackages": 30,
      "packageType": "BOXES",
      "grossWeight": 11629.77,
      "measurement": 31.93
    },
    {
      "containerNumber": "CONT1564920",
      "sealNumber": "SEAL460156",
      "numberOfPackages": 46,
      "packageType": "BOXES",
      "grossWeight": 6129.53,
      "measurement": 35.31
    }
  ],
  "totalShipment": {
    "totalContainers": "6 x 40 STANDARD GENERAL",
    "totalPackages": 345,
    "totalGrossWeight": 70870.86,
    "totalMeasurement": 196.34
  },
  "additionalInformation": {
    "lcDetails": {
      "lcNumber": "LC1234567890"
    },
    "certificateDetails": [],
    "originalBLDistribution": {
      "name": "WORLDWIDE SHIPPING LTD.",
      "address": "888 WORLDWIDE WAY, ROTTERDAM, NETHERLANDS 3011 DP",
      "telephone": "+31 10 200 3000",
      "fax": "+31 10 200 3001",
      "email": "JANSSEN.MARK@WORLDWIDESHIPPING.NL"
    },
    "originalInvoiceDistribution": {
      "name": "ASIA PACIFIC MANUFACTURING CO. LTD.",
      "address": "1234 TOY ROAD, NINGBO, ZHEJIANG, CHINA 315000",
      "telephone": "+86 574 5678 9012",
      "fax": "+86 574 5678 9013"
    },
    "onboardDate": "2024-11-06 18:00",
    "additionalRemarks": "21 DAYS FREE TIME AT DESTINATION, MAINTAIN HUMIDITY"
  }
}