{
  "bookingReference": "CHERRY202410023303",
  "voyageDetails": {
    "vesselName": "SHIP_670",
    "voyageNumber": "1669"
  },
  "routeDetails": {
    "placeOfReceipt": "NINGBO, CHINA",
    "portOfLoading": "NINGBO, CHINA",
    "portOfDischarge": "LE HAVRE, FRANCE",
    "placeOfDelivery": "LE HAVRE, FRANCE"
  },
  "paymentDetails": {
    "freightPaymentTerms": "PREPAID",
    "freightPayableAt": "NINGBO, CHINA"
  },
  "documentationDetails": {
    "blType": "ORIGINAL",
    "numberOfOriginalBLs": 3,
    "numberOfCopies": 7
  },
  "partyDetails": {
    "shipper": {
      "name": "PRECISION TECHNOLOGIES INC",
      "address": "123 DIGITAL LANE, YINZHOU DISTRICT, NINGBO CITY, ZHEJIANG PROVINCE, 314000, CHINA",
      "country": "CHINA",
      "additionalInfo": "",
      "telephone": "+86 574 1234 5678",
      "email": "JEREMY.LEE@PRECISIONTECHNOLOGIES.CN"
    },
    "consignee": {
      "name": "GLOBAL LOGISTICS LTD.",
      "address": "WILHELMINAKADE 123, 3072 AP ROTTERDAM, 3072 AP, FRANCE",
      "country": "FRANCE",
      "email": "WILLEM_VAN_DER_BERG@GLOBALLOGISTICS.FR",
      "telephone": "+33 15 987 6910",
      "fax": "+33 15 987 6913"
    },
    "notifyParty": {
      "name": "DUTCH GLOBAL LOGISTICS B.V.",
      "address": "MAASVLAKTE BOULEVARD 500, HARBOR DISTRICT, 3199 LZ, ROTTERDAM, THE NETHERLANDS",
      "country": "NETHERLANDS",
      "email": "PIETER_DE_VRIES@DUTCHGLOBALLOGISTICS.NL",
      "telephone": "+31 10 289 4000",
      "fax": "+31 10 289 4001"
    }
  },
  "shippingTerm": "CY/CY",
  "hsCode": "030219",
  "commodityDescription": "FROZEN FISH FILLETS",
  "containers": [
    {
      "containerNumber": "CRLU4927001",
      "sealNumber": "713194",
      "marksAndNumbers": "NO MARK",
      "numberOfPackages": 800,
      "packageType": "CARTONS",
      "cargoDescription": "FROZEN FISH FILLETS",
      "grossWeight": 15000.0,
      "measurement": 56.0
    },
    {
      "containerNumber": "CRLU4961926",
      "sealNumber": "713176",
      "marksAndNumbers": "NO MARK",
      "numberOfPackages": 800,
      "packageType": "CARTONS",
      "cargoDescription": "FROZEN FISH FILLETS",
      "grossWeight": 15000.0,
      "measurement": 56.0
    },
    {
      "containerNumber": "CRLU4976543",
      "sealNumber": "713180",
      "marksAndNumbers": "NO MARK",
      "numberOfPackages": 800,
      "packageType": "CARTONS",
      "cargoDescription": "FROZEN FISH FILLETS",
      "grossWeight": 15000.0,
      "measurement": 56.0
    }
  ],
  "totalShipment": {
    "totalContainers": "THREE (45 HC X 3) HIGH CUBIC CONTAINERS ONLY",
    "totalPackages": 2400,
    "totalGrossWeight": 45000.0,
    "totalMeasurement": 168.0
  },
  "additionalInformation": {
    "lcDetails": {
      "lcNumber": ""
    },
    "certificateDetails": [],
    "originalBLDistribution": {
      "name": "GLOBAL LOGISTICS LTD.",
      "address": "888 CENTURY AVENUE, YINZHOU DISTRICT, NINGBO CITY, ZHEJIANG PROVINCE 312100, CHINA",
      "telephone": "+86 574 8765 4321",
      "fax": "+86 574 8765 4322",
      "email": "ZENLEE@GLOBALLOGISTICS.CN"
    },
    "originalInvoiceDistribution": {
      "name": "GLOBAL LOGISTICS LTD.",
      "address": "888 CENTURY AVENUE, YINZHOU DISTRICT, NINGBO CITY, ZHEJIANG PROVINCE 312100, CHINA",
      "telephone": "+86 574 8765 4321",
      "fax": "+86 574 8765 4322",
      "email": "ZENLEE@GLOBALLOGISTICS.CN"
    },
    "onboardDate": "2024-10-16 18:00",
    "additionalRemarks": "CONTAINER TYPE: REEFER, TEMPERATURE CONTROLLED CARGO: -13째C, UNDER DECK TOP STOWAGE"
  },
  "reeferSettings": {
    "containerNumber": "CONT1262334",
    "temperature": "-13째C",
    "minTemperature": "-15째C",
    "maxTemperature": "-11째C",
    "ventilation": "47%",
    "humidity": "93%"
  },
  "containerDetails": {
    "type": "REEFER CONTAINER"
  }
}