{
  "bookingReference": "CHERRY202411187547",
  "customerName": "GREEN EARTH IMPORTS LLC",
  "shipperName": "SHANGHAI GLOBAL TRADING CO. LTD.",
  "invoiceReceiver": "GREEN EARTH IMPORTS LLC",
  "voyageDetails": {
    "vesselName": "SHIP_5471",
    "voyageNumber": "6470"
  },
  "cargoDetails": {
    "hsCode": "940330",
    "chapterDescription": "OTHER FURNITURE AND PARTS THEREOF",
    "commodity": "GENERAL"
  },
  "containerDetails": {
    "size": "20 STANDARD",
    "type": "DRY CONTAINER",
    "quantity": 1
  },
  "routeDetails": {
    "placeOfReceipt": "SHANGHAI, CHINA",
    "portOfLoading": "SHANGHAI, CHINA",
    "portOfDischarge": "ROTTERDAM, NETHERLANDS",
    "placeOfDelivery": "ROTTERDAM, NETHERLANDS"
  },
  "scheduleDetails": {
    "estimatedArrivalAtLoadingPort": "2024-12-01 15:00",
    "estimatedDepartureFromLoadingPort": "2024-12-03 10:00",
    "estimatedArrivalAtDischargePort": "2025-01-10 18:00"
  },
  "emptyContainerPickupLocation": "SHANGHAI, CHINA",
  "shippingTerm": "CFS/CY",
  "remarks": "CONTAINER TYPE: GENERAL, THIS SIDE UP",
  "cargoType": "GENERAL"
}