{
  "bookingReference": "CHERRY202411028993",
  "customerName": "GLOBAL LOGISTICS SOLUTIONS",
  "shipperName": "ASIA PACIFIC TRADING CO.",
  "invoiceReceiver": "GLOBAL LOGISTICS SOLUTIONS",
  "voyageDetails": {
    "vesselName": "SHIP_30",
    "voyageNumber": "1029"
  },
  "cargoDetails": {
    "hsCode": "961700",
    "chapterDescription": "TRAVEL GOODS, HANDBAGS AND SIMILAR CONTAINERS, ARTICLES OF PERSONAL ADORNMENT (JEWELLERY, WATCHES, CLOCKS, ETC.) AND MISCELLANEOUS ARTICLES OF BEAUTY OR PERSONAL HYGIENE",
    "commodity": "GENERAL"
  },
  "containerDetails": {
    "size": "20 STANDARD",
    "type": "GENERAL",
    "quantity": 2
  },
  "routeDetails": {
    "placeOfReceipt": "NINGBO",
    "portOfLoading": "NINGBO",
    "portOfDischarge": "GDANSK",
    "placeOfDelivery": "GDANSK"
  },
  "scheduleDetails": {
    "estimatedArrivalAtLoadingPort": "2024-11-15 14:00",
    "estimatedDepartureFromLoadingPort": "2024-11-16 09:00",
    "estimatedArrivalAtDischargePort": "2024-12-06 08:00"
  },
  "emptyContainerPickupLocation": "NINGBO, CHINA",
  "shippingTerm": "CFS/CY",
  "remarks": "30 DAYS FREE TIME AT DESTINATION",
  "cargoType": "GENERAL"
}