{
  "bookingReference": "CHERRY202411097585",
  "customerName": "GLOBAL FORWARDING SOLUTIONS LTD",
  "shipperName": "SUNRISE TRADING CO.",
  "invoiceReceiver": "SUNRISE GLOBAL LOGISTICS LTD",
  "voyageDetails": {
    "vesselName": "SHIP_4314",
    "voyageNumber": "5313"
  },
  "cargoDetails": {
    "hsCode": "94034000",
    "chapterDescription": "FURNITURE",
    "commodity": "WOODEN CHAIRS"
  },
  "containerDetails": {
    "size": "40 HIGH CUBE CONTAINER",
    "type": "HIGH CUBE",
    "quantity": 5
  },
  "routeDetails": {
    "placeOfReceipt": "NINGBO, CHINA",
    "portOfLoading": "NINGBO, CHINA",
    "portOfDischarge": "ROTTERDAM, NETHERLANDS",
    "placeOfDelivery": "ROTTERDAM, NETHERLANDS"
  },
  "scheduleDetails": {
    "estimatedArrivalAtLoadingPort": "2024-11-15 12:00",
    "estimatedDepartureFromLoadingPort": "2024-11-16 16:00",
    "estimatedArrivalAtDischargePort": "2024-12-04 08:00"
  },
  "emptyContainerPickupLocation": "NINGBO, CHINA",
  "shippingTerm": "FOB",
  "remarks": "40' HIGH CUBE CONTAINERS, VALUE: USD25,000"
}